codium_mirror/__init__.py
codium_mirror/codium.mirrors
codium_mirror-0.0.4.dist-info/METADATA
codium_mirror-0.0.4.dist-info/WHEEL
codium_mirror-0.0.4.dist-info/entry_points.txt
codium_mirror-0.0.4.dist-info/top_level.txt
codium_mirror-0.0.4.dist-info/RECORD
