Metadata-Version: 2.1
Name: codium-mirror
Version: 0.0.4
Summary: codium_mirror
Home-page: https://github.com/larryw3i/codium_mirror
Author: larryw3i & Contributors
Author-email: 
License: UNKNOWN
Platform: UNKNOWN
Classifier: Programming Language :: Python :: 3
Classifier: License :: OSI Approved :: MIT License
Classifier: Operating System :: OS Independent
Requires-Python: >=3.6
